{
  "info": {
    "name": "FIT4110 Lab04 Camera Docker Verification",
    "description": "Postman collection used to verify the Dockerized camera service in Lab 04.",
    "schema": "https://schema.getpostman.com/json/collection/v2.1.0/collection.json"
  },
  "item": [
    {
      "name": "01_Functional",
      "item": [
        {
          "name": "GET health returns 200",
          "request": {
            "method": "GET",
            "header": [],
            "url": {
              "raw": "{{baseUrl}}/health",
              "host": [
                "{{baseUrl}}"
              ],
              "path": [
                "health"
              ]
            }
          },
          "event": [
            {
              "listen": "test",
              "script": {
                "type": "text/javascript",
                "exec": [
                  "pm.test('Status code is 200', function () { pm.response.to.have.status(200); });",
                  "pm.test('Response has status ok', function () { const json = pm.response.json(); pm.expect(json.status).to.eql('ok'); });",
                  "pm.test('Response has service name and version', function () { const json = pm.response.json(); pm.expect(json).to.have.property('service'); pm.expect(json).to.have.property('version'); });"
                ]
              }
            }
          ]
        },
        {
          "name": "GET root returns service metadata",
          "request": {
            "method": "GET",
            "header": [],
            "url": {
              "raw": "{{baseUrl}}/",
              "host": [
                "{{baseUrl}}"
              ],
              "path": []
            }
          },
          "event": [
            {
              "listen": "test",
              "script": {
                "type": "text/javascript",
                "exec": [
                  "pm.test('Status code is 200', function () { pm.response.to.have.status(200); });",
                  "pm.test('Response includes service and status', function () { const json = pm.response.json(); pm.expect(json).to.have.property('service'); pm.expect(json).to.have.property('status'); pm.expect(json.status).to.eql('running'); });"
                ]
              }
            }
          ]
        }
      ]
    }
  ]
}
